pySMSgateway/__init__.py
pySMSgateway/pysmsgateway.py
pysmsgateway-0.1.0.dist-info/METADATA
pysmsgateway-0.1.0.dist-info/WHEEL
pysmsgateway-0.1.0.dist-info/top_level.txt
pysmsgateway-0.1.0.dist-info/RECORD
