Metadata-Version: 2.1
Name: pysmsgateway
Version: 0.1.0
Summary: A Python library for sending SMS messages via a custom gateway
Author: Thomson Kaisi
Author-email: tkaisi@andrew.cmu.edu
Classifier: License :: OSI Approved :: MIT License
Classifier: Programming Language :: Python :: 3
Classifier: Operating System :: OS Independent
Requires-Dist: requests
